balebot/__init__.py
balebot/__version__.py
balebot/bale_future.py
balebot/bot.py
balebot/config.py
balebot/dispatcher.py
balebot/updater.py
balebot/connection/__init__.py
balebot/connection/network.py
balebot/filters/__init__.py
balebot/filters/bank_message_filter.py
balebot/filters/contact_filter.py
balebot/filters/default.py
balebot/filters/document_filter.py
balebot/filters/filter.py
balebot/filters/json_filter.py
balebot/filters/location_filter.py
balebot/filters/photo_filter.py
balebot/filters/sticker_filter.py
balebot/filters/template_message_filter.py
balebot/filters/template_response_filter.py
balebot/filters/text_filter.py
balebot/filters/unsupported_filter.py
balebot/filters/video_filter.py
balebot/filters/voice_filter.py
balebot/handlers/__init__.py
balebot/handlers/command_handler.py
balebot/handlers/handler.py
balebot/handlers/message_handler.py
balebot/handlers/quoted_message_handler.py
balebot/models/__init__.py
balebot/models/base_models/__init__.py
balebot/models/base_models/avatar.py
balebot/models/base_models/bot_api_quoted_message.py
balebot/models/base_models/bot_command.py
balebot/models/base_models/bot_quoted_message.py
balebot/models/base_models/contact.py
balebot/models/base_models/contact_record.py
balebot/models/base_models/fat_seq_update.py
balebot/models/base_models/file_location.py
balebot/models/base_models/group.py
balebot/models/base_models/group_member.py
balebot/models/base_models/group_peer.py
balebot/models/base_models/image_location.py
balebot/models/base_models/jsonable.py
balebot/models/base_models/member.py
balebot/models/base_models/pack_info.py
balebot/models/base_models/peer.py
balebot/models/base_models/raw_json.py
balebot/models/base_models/request.py
balebot/models/base_models/request_body.py
balebot/models/base_models/response.py
balebot/models/base_models/response_body.py
balebot/models/base_models/user.py
balebot/models/base_models/user_peer.py
balebot-1.8.15.dist-info/METADATA
balebot-1.8.15.dist-info/RECORD
balebot-1.8.15.dist-info/WHEEL
balebot-1.8.15.dist-info/top_level.txt
