Metadata-Version: 2.1
Name: balebot
Version: 1.8.15
Summary: Python framework for Bale messenger Bot API
Home-page: https://github.com/balemessenger/bale-bot-python
Author: bale
Author-email: balebot@elenoon.ir
License: Apache 2.0
Platform: UNKNOWN
Requires-Dist: aiohttp (==2.3.7)
Requires-Dist: asyncio (==3.4.3)
Requires-Dist: graypy (==0.2.14)
Requires-Dist: pillow (==5.2.0)
Requires-Dist: redis (==3.0.1)
